{"openapi":"3.0.0","paths":{"/recipes":{"get":{"operationId":"RecipesController_getByUserId","parameters":[],"responses":{"200":{"description":"List of recipes"}},"security":[{"X-Session-ID":[]}],"summary":"Get all recipes for current user","tags":["recipes"]},"post":{"operationId":"RecipesController_create","parameters":[],"requestBody":{"required":true,"content":{"application/json":{"schema":{"$ref":"#/components/schemas/CreateRecipeDto"}}}},"responses":{"201":{"description":"Recipe created"}},"security":[{"X-Session-ID":[]}],"summary":"Create new recipe","tags":["recipes"]},"put":{"operationId":"RecipesController_update","parameters":[],"requestBody":{"required":true,"content":{"application/json":{"schema":{"$ref":"#/components/schemas/UpdateRecipeDto"}}}},"responses":{"200":{"description":"Recipe updated"}},"security":[{"X-Session-ID":[]}],"summary":"Update recipe","tags":["recipes"]},"delete":{"operationId":"RecipesController_delete","parameters":[],"requestBody":{"required":true,"content":{"application/json":{"schema":{"type":"object","properties":{"id":{"type":"string","description":"Recipe ID"}}}}}},"responses":{"200":{"description":"Recipe deleted"}},"security":[{"X-Session-ID":[]}],"summary":"Delete recipe","tags":["recipes"]}},"/recipes/{id}":{"get":{"operationId":"RecipesController_getById","parameters":[{"name":"id","required":true,"in":"path","description":"Recipe ID","schema":{"type":"string"}}],"responses":{"200":{"description":"Recipe found"},"404":{"description":"Recipe not found"}},"security":[{"X-Session-ID":[]}],"summary":"Get recipe by ID","tags":["recipes"]}},"/collections":{"get":{"operationId":"CollectionsController_getByUserId","parameters":[],"responses":{"200":{"description":"List of collections"}},"security":[{"X-Session-ID":[]}],"summary":"Get all collections for current user","tags":["collections"]},"post":{"operationId":"CollectionsController_create","parameters":[],"requestBody":{"required":true,"content":{"application/json":{"schema":{"$ref":"#/components/schemas/CreateCollectionDto"}}}},"responses":{"201":{"description":"Collection created"}},"security":[{"X-Session-ID":[]}],"summary":"Create new collection","tags":["collections"]},"put":{"operationId":"CollectionsController_update","parameters":[],"requestBody":{"required":true,"content":{"application/json":{"schema":{"$ref":"#/components/schemas/UpdateCollectionDto"}}}},"responses":{"200":{"description":"Collection updated"}},"security":[{"X-Session-ID":[]}],"summary":"Update collection","tags":["collections"]},"delete":{"operationId":"CollectionsController_delete","parameters":[],"requestBody":{"required":true,"content":{"application/json":{"schema":{"type":"object","properties":{"id":{"type":"string","description":"Collection ID"}}}}}},"responses":{"200":{"description":"Collection deleted"}},"security":[{"X-Session-ID":[]}],"summary":"Delete collection","tags":["collections"]}},"/collections/{id}":{"get":{"operationId":"CollectionsController_getById","parameters":[{"name":"id","required":true,"in":"path","description":"Collection ID","schema":{"type":"string"}}],"responses":{"200":{"description":"Collection found"},"404":{"description":"Collection not found"}},"security":[{"X-Session-ID":[]}],"summary":"Get collection by ID","tags":["collections"]}},"/collections/{id}/recipes":{"post":{"operationId":"CollectionsController_addRecipe","parameters":[{"name":"id","required":true,"in":"path","description":"Collection ID","schema":{"type":"string"}}],"requestBody":{"required":true,"content":{"application/json":{"schema":{"$ref":"#/components/schemas/AddRecipeToCollectionDto"}}}},"responses":{"201":{"description":"Recipe added to collection"}},"security":[{"X-Session-ID":[]}],"summary":"Add recipe to collection","tags":["collections"]}},"/collections/{id}/recipes/{recipeId}":{"delete":{"operationId":"CollectionsController_removeRecipe","parameters":[{"name":"id","required":true,"in":"path","description":"Collection ID","schema":{"type":"string"}},{"name":"recipeId","required":true,"in":"path","description":"Recipe ID","schema":{"type":"string"}}],"responses":{"200":{"description":"Recipe removed from collection"}},"security":[{"X-Session-ID":[]}],"summary":"Remove recipe from collection","tags":["collections"]}}},"info":{"title":"Cookly Content Service","description":"API for managing recipes and collections","version":"1.0","contact":{}},"tags":[{"name":"recipes","description":"Recipe operations"},{"name":"collections","description":"Collection operations"}],"servers":[],"components":{"securitySchemes":{"X-Session-ID":{"type":"apiKey","in":"header","name":"X-Session-ID","description":"Session identifier"}},"schemas":{"CreateRecipeDto":{"type":"object","properties":{"name":{"type":"string","description":"Recipe name"},"description":{"type":"string","description":"Optional recipe description","nullable":true},"instructions":{"type":"string","description":"Cooking instructions"}},"required":["name","description","instructions"]},"UpdateRecipeDto":{"type":"object","properties":{"id":{"type":"string","description":"Recipe ID"},"name":{"type":"string","description":"Recipe name"},"description":{"type":"string","description":"Optional recipe description","nullable":true},"instructions":{"type":"string","description":"Cooking instructions"}},"required":["id"]},"CreateCollectionDto":{"type":"object","properties":{"name":{"type":"string","description":"Collection name"},"description":{"type":"string","description":"Optional collection description","nullable":true}},"required":["name","description"]},"UpdateCollectionDto":{"type":"object","properties":{"id":{"type":"string","description":"Collection ID"},"name":{"type":"string","description":"Collection name"},"description":{"type":"string","description":"Optional collection description","nullable":true}},"required":["id"]},"AddRecipeToCollectionDto":{"type":"object","properties":{"collectionId":{"type":"string","description":"Collection ID"},"recipeId":{"type":"string","description":"Recipe ID"}},"required":["collectionId","recipeId"]}}}}